oarepo_runtime/__init__.py
oarepo_runtime/config.py
oarepo_runtime/ext.py
oarepo_runtime/ext_config.py
oarepo_runtime/profile.py
oarepo_runtime/proxies.py
oarepo_runtime/tasks.py
oarepo_runtime/uow.py
oarepo_runtime/cli/__init__.py
oarepo_runtime/cli/assets.py
oarepo_runtime/cli/base.py
oarepo_runtime/cli/cf.py
oarepo_runtime/cli/check.py
oarepo_runtime/cli/configuration.py
oarepo_runtime/cli/fixtures.py
oarepo_runtime/cli/index.py
oarepo_runtime/cli/validate.py
oarepo_runtime/cli/permissions/__init__.py
oarepo_runtime/cli/permissions/base.py
oarepo_runtime/cli/permissions/evaluate.py
oarepo_runtime/cli/permissions/list.py
oarepo_runtime/cli/permissions/search.py
oarepo_runtime/datastreams/__init__.py
oarepo_runtime/datastreams/asynchronous.py
oarepo_runtime/datastreams/catalogue.py
oarepo_runtime/datastreams/datastreams.py
oarepo_runtime/datastreams/errors.py
oarepo_runtime/datastreams/ext.py
oarepo_runtime/datastreams/fixtures.py
oarepo_runtime/datastreams/json.py
oarepo_runtime/datastreams/semi_asynchronous.py
oarepo_runtime/datastreams/synchronous.py
oarepo_runtime/datastreams/transformers.py
oarepo_runtime/datastreams/types.py
oarepo_runtime/datastreams/utils.py
oarepo_runtime/datastreams/readers/__init__.py
oarepo_runtime/datastreams/readers/attachments.py
oarepo_runtime/datastreams/readers/excel.py
oarepo_runtime/datastreams/readers/json.py
oarepo_runtime/datastreams/readers/service.py
oarepo_runtime/datastreams/readers/yaml.py
oarepo_runtime/datastreams/writers/__init__.py
oarepo_runtime/datastreams/writers/attachments_file.py
oarepo_runtime/datastreams/writers/attachments_service.py
oarepo_runtime/datastreams/writers/publish.py
oarepo_runtime/datastreams/writers/service.py
oarepo_runtime/datastreams/writers/utils.py
oarepo_runtime/datastreams/writers/validation_errors.py
oarepo_runtime/datastreams/writers/yaml.py
oarepo_runtime/i18n/__init__.py
oarepo_runtime/info/__init__.py
oarepo_runtime/info/check.py
oarepo_runtime/info/views.py
oarepo_runtime-1.10.4.dist-info/licenses/LICENSE
oarepo_runtime-1.10.4.dist-info/METADATA
oarepo_runtime-1.10.4.dist-info/WHEEL
oarepo_runtime-1.10.4.dist-info/entry_points.txt
oarepo_runtime-1.10.4.dist-info/top_level.txt
oarepo_runtime-1.10.4.dist-info/RECORD
