Metadata-Version: 2.4
Name: oarepo-runtime
Version: 1.10.4
Summary: A set of runtime extensions of Invenio repository
License-File: LICENSE
Requires-Dist: marshmallow
Requires-Dist: langcodes
Requires-Dist: pyyaml
Requires-Dist: openpyxl
Requires-Dist: flask-babelex
Requires-Dist: deepmerge
Requires-Dist: tqdm
Requires-Dist: deprecated
Requires-Dist: idutils
Provides-Extra: dev
Requires-Dist: pytest>=7.1.2; extra == "dev"
Requires-Dist: black; extra == "dev"
Requires-Dist: isort; extra == "dev"
Requires-Dist: autoflake; extra == "dev"
Requires-Dist: oarepo-tools; extra == "dev"
Provides-Extra: tests
Requires-Dist: pytest>=7.1.2; extra == "tests"
Requires-Dist: pytest-oarepo; extra == "tests"
Requires-Dist: psutil; extra == "tests"
Dynamic: license-file
